.gitignore
CHANGES.rst
CONTRIBUTORS.rst
MANIFEST.in
README.rst
setup.py
docs/LICENSE.GPL
docs/LICENSE.rst
src/collective/__init__.py
src/collective.js.rgraph.egg-info/PKG-INFO
src/collective.js.rgraph.egg-info/SOURCES.txt
src/collective.js.rgraph.egg-info/dependency_links.txt
src/collective.js.rgraph.egg-info/entry_points.txt
src/collective.js.rgraph.egg-info/namespace_packages.txt
src/collective.js.rgraph.egg-info/not-zip-safe
src/collective.js.rgraph.egg-info/requires.txt
src/collective.js.rgraph.egg-info/top_level.txt
src/collective/js/__init__.py
src/collective/js/rgraph/__init__.py
src/collective/js/rgraph/configure.zcml
src/collective/js/rgraph/resources/RGraph.bar.js
src/collective/js/rgraph/resources/RGraph.bipolar.js
src/collective/js/rgraph/resources/RGraph.common.adjusting.js
src/collective/js/rgraph/resources/RGraph.common.annotate.js
src/collective/js/rgraph/resources/RGraph.common.context.js
src/collective/js/rgraph/resources/RGraph.common.core.js
src/collective/js/rgraph/resources/RGraph.common.effects.js
src/collective/js/rgraph/resources/RGraph.common.key.js
src/collective/js/rgraph/resources/RGraph.common.resizing.js
src/collective/js/rgraph/resources/RGraph.common.tooltips.js
src/collective/js/rgraph/resources/RGraph.common.zoom.js
src/collective/js/rgraph/resources/RGraph.fuel.js
src/collective/js/rgraph/resources/RGraph.funnel.js
src/collective/js/rgraph/resources/RGraph.gantt.js
src/collective/js/rgraph/resources/RGraph.gauge.js
src/collective/js/rgraph/resources/RGraph.hbar.js
src/collective/js/rgraph/resources/RGraph.hprogress.js
src/collective/js/rgraph/resources/RGraph.led.js
src/collective/js/rgraph/resources/RGraph.line.js
src/collective/js/rgraph/resources/RGraph.meter.js
src/collective/js/rgraph/resources/RGraph.modaldialog.js
src/collective/js/rgraph/resources/RGraph.odo.js
src/collective/js/rgraph/resources/RGraph.pie.js
src/collective/js/rgraph/resources/RGraph.radar.js
src/collective/js/rgraph/resources/RGraph.rose.js
src/collective/js/rgraph/resources/RGraph.rscatter.js
src/collective/js/rgraph/resources/RGraph.scatter.js
src/collective/js/rgraph/resources/RGraph.skeleton.js
src/collective/js/rgraph/resources/RGraph.thermometer.js
src/collective/js/rgraph/resources/RGraph.vprogress.js
src/collective/js/rgraph/resources/RGraph.waterfall.js
src/collective/js/rgraph/resources/excanvas.js
