Metadata-Version: 1.1
Name: collective.js.rgraph
Version: 1.0.1
Summary: RGraph javascript library for Plone
Home-page: http://pypi.python.org/pypi/collective.js.rgraph
Author: Cédric Messiant
Author-email: cedricmessiant@ecreall.com
License: GPL
Keywords: javascript,charts,Plone
Platform: UNKNOWN
Classifier: Environment :: Web Environment
Classifier: Framework :: Plone
Classifier: Programming Language :: Python
Classifier: Programming Language :: Python :: 2.7
